setuptools_black/__init__.py
setuptools_black/setuptools_command.py
tests/__init__.py
tests/test_command.py
setuptools_black-0.1.5.dist-info/METADATA
setuptools_black-0.1.5.dist-info/WHEEL
setuptools_black-0.1.5.dist-info/entry_points.txt
setuptools_black-0.1.5.dist-info/top_level.txt
setuptools_black-0.1.5.dist-info/zip-safe
setuptools_black-0.1.5.dist-info/RECORD
