Metadata-Version: 2.1
Name: setuptools-black
Version: 0.1.5
Summary: black command for setuptools
Home-page: https://github.com/agrenott/setuptools-black
Author: Aurelien Grenotton
Author-email: agrenott@gmail.com
License: MIT
Keywords: black setuptools plugin
Platform: UNKNOWN
Classifier: Framework :: Setuptools Plugin
Classifier: Development Status :: 4 - Beta
Classifier: Programming Language :: Python :: 3
Classifier: Intended Audience :: Developers
Classifier: Operating System :: OS Independent
Classifier: License :: OSI Approved :: MIT License
Classifier: Topic :: Software Development :: Libraries :: Python Modules
Requires-Dist: black (>=18.9b0)
